{
    "20042700000208": {
        "基本信息": {
            "出院诊断": "胰腺恶性肿瘤(导管腺癌，术后复发，IV期，ECOG1分)",
            "床号": "8551",
            "科别": "肿瘤科一病区",
            "入院时间": "2020-04-27 10:30",
            "出院时间": "2020-04-28 09:30",
            "姓名": "测试病人0279",
            "性别": "女",
            "年龄": "79",
            "住院号": "z83531",
            "入院诊断": "胰腺恶性肿瘤(导管腺癌，术后复发，IV期,ECOG1分)"
        },
        "入院时简要病史": "患者2016年1月份社区体检发现CA199升高，到瑞金医院检查发现为胰腺癌，2016-1-27行胰腺癌根治术，【术后病理】胰腺尾导管腺癌Ⅱ级，R0，淋巴结未见癌转移。术后未进行化疗，定期复查未见复发转移征象。2019-5-28查血常规、肝肾功能、生化正常，CA199高：6969.7u/ml。上腹部平扫CT提示：胰腺术后所见，左侧肾上腺稍增粗，腹膜后小淋巴结显示，腹主动脉壁钙化，两肺下叶多枚结节，拟转移。6-19、7-3、7-17、7-31、8-4、8-30、9-16、10-5、12-31、2020-1-14、2-1、2-14、2-27、3-12、3-26、4-11行AG方案化疗，具体：白蛋白紫杉醇100mg+吉西他滨（泽菲）1.2g静滴。现到我院进一步诊治收入我科。     患者无恶心、呕吐，无黄疸、发热，无腹痛、腹胀和腰部酸痛，食欲睡眠可，大小便正常，体重无下降。",
        "体检摘要": "神清，精神可，一般情况可",
        "生命体征": {
            "T": "36.5",
            "P": "80",
            "R": "20",
            "BP高": "160",
            "BP低": "50"
        },
        "住院期间医疗情况": "C-反应蛋白 3.6mg/L  白细胞计数 4.23×10^9/L  中性粒细胞% 36.8↓％  淋巴细胞% 47.0↑％  单核细胞% 11.3↑％  嗜酸性粒细胞% 4.6％  嗜碱性粒细胞% 0.3％  中性粒细胞计数 1.56↓×10^9/L  淋巴细胞计数 1.99×10^9/L  单核细胞计数 0.48×10^9/L  嗜酸性粒细胞计数 0.19×10^9/L  嗜碱性粒细胞计数 0.01×10^9/L  红细胞计数 3.10↓×10^12/L  血红蛋白 99↓g/L  红细胞比容 0.299↓  平均红细胞体积 96.4fl  平均血红蛋白量 31.8pg  平均血红蛋白浓度 329g/L  红细胞分布宽度 14.7↑％  血小板计数 387↑×10^9/L  血小板平均体积 10.1fl  前白蛋白 200mg/L  丙氨酸氨基转移酶 8↓IU/L  天门冬氨酸氨基转移酶 19IU/L  碱性磷酸酶 109IU/L  γ-谷氨酰基转移酶 14IU/L  总胆红素 5.5μmol/L  直接胆红素 0.0μmol/L  总蛋白 71g/L  白蛋白 42g/L  白球比例 1.45  胆汁酸 13.2↑μmol/L  尿素 4.7mmol/L  肌酐 49↓μmol/L  尿酸 303μmol/L  钠 140mmol/L  钾 4.19mmol/L  氯 105mmol/L  二氧化碳 25.0mmol/L  钙 2.37mmol/L  磷 1.23mmol/L  估算肾小球滤过率 89.3ml/min/1.73m2  甲胎蛋白 1.81ng/mL  癌胚抗原 1.43ng/mL  神经元特异性烯醇化酶 18.95↑ng/mL  细胞角蛋白19 1.91ng/mL  鳞状细胞癌相关抗原 0.50ng/mL  糖类抗原125 9.0U/mL  糖类抗原724 50.18↑U/mL  糖类抗原199 99.6↑U/mL  糖类抗原242 46.5↑U/mL  糖类抗原153 7.4U/mL",
        "出院时情况": "一般情况可",
        "病程与治疗情况": "患者入院后完善相关检查， 排除化疗禁忌，于2020-4-26行AG方案化疗，具体：白蛋白紫杉醇100mg+吉西他滨（泽菲）1.2g静滴，患者无不适， 经主任批准后予出院。",
        "出院后用药建议": "    1，休息，营养饮食；     2，定期复查血常规，肝肾功能，如有异常，及时复诊；     3，肿瘤科随诊。",
        "病人信息": {
            "姓名": "测试病人0279",
            "性别": "女",
            "科室": "肿瘤科一病区",
            "床号": "8551",
            "住院号": "z83531",
            "住院流水号": "20042700000208",
            "年龄": "79",
            "出生年月": "1940-10-06",
            "入院时间": "2020-04-28",
            "出院时间": ""
        }
    }
}