{
    "20033100000240": {
        "基本信息": {
            "出院诊断": "恶性肿瘤维持性化学治疗,胃恶性肿瘤(腺癌，腹膜转移，IV期，ECOG 1分)",
            "床号": "8551",
            "科别": "肿瘤科一病区",
            "入院时间": "2020-03-31 12:53",
            "出院时间": "2020-04-02 13:30",
            "姓名": "测试病人0279",
            "性别": "男",
            "年龄": "58",
            "住院号": "z83531",
            "入院诊断": "胃恶性肿瘤(腺癌，腹膜转移，IV期，ECOG 1分)"
        },
        "入院时简要病史": "患者2019-11-05无明显诱因下出现上腹胀，餐后为主，伴纳差，反酸、嗳气，恶心，偶有呕吐少量咖啡色液体，无黑便便血，无腹痛，无黄疸厌油，随即至我院查胃镜示胃体小弯侧一巨大溃疡，表面覆污苔活检钳触之较韧，易出血，累及胃体小弯及部分前后壁、胃角及部分胃窦，病灶堵塞胃腔。溃疡灶边缘局部活检病理提示 低分化腺癌，部分印戒细胞癌，HP(+)，免疫组化：AE1/AE3 （+），CK7（少量+），P53(+)，Ki67（70%），PGM-1（组织细胞+），EBV原位杂交：EBER（-），PD-L1（22C3）（CPS＜1），PD-L1（22C3）阳性对照（+）。至我科就诊 ，行CT示1.胃体-胃窦溃疡浸润性病灶，胃Ca侵及浆膜层外考虑；胃周多发淋巴结显示；腹腔内脂肪间隙浑浊伴多发小条索影，网膜转移考虑；腹水、盆腔积液；2.肝右叶钙化灶，肝S7段类圆形低密度灶，性质待定；两肾囊肿；前列腺稍大；请结合临床和其他检查，随访。经多学科讨论后考虑患者系晚期胃癌合并幽门不全梗阻，予以消化道支架置入解除梗阻。 患者入院后完善各项检查，排除禁忌，于2019-12-13、2020-1-3、1-29、2-18、3-10行白蛋白紫杉醇 300mg + 奥沙利铂 185mg治疗。现为进一步诊治，门诊拟“胃恶性肿瘤”收治入院。     自起病以来，患者神清，精神可，纳差，小便如常，大便2-3天/次，近一个月体重下降8kg。",
        "体检摘要": "神清，气平，皮肤巩膜无黄染，心肺无殊，腹软，无压痛，双下肢无浮肿",
        "生命体征": {
            "T": "36.9",
            "P": "86",
            "R": "18",
            "BP高": "100",
            "BP低": "85"
        },
        "住院期间医疗情况": "C反应蛋白 26↑mg/L  仪器名称 BC-6800_2  白细胞计数 13.96↑x10^9/L  中性粒细胞% 85.9↑％  淋巴细胞% 8.7↓％  单核细胞% 5.3％  嗜酸性粒细胞% 0.0↓％  嗜碱性粒细胞% 0.1％  中性粒细胞计数 11.99↑×10^9/L  淋巴细胞计数 1.22×10^9/L  单核细胞计数 0.74×10^9/L  嗜酸性粒细胞计数 0.00↓×10^9/L  嗜碱性粒细胞计数 0.01×10^9/L  红细胞计数 2.12↓×10^12/L  血红蛋白 76↓g/L  红细胞比容 0.237↓  平均红细胞体积 112.0↑fl  平均血红蛋白量 35.9↑pg  平均血红蛋白浓度 321g/L  红细胞分布宽度 29.5↑％  血小板计数 260×10^9/L  血小板平均体积 7.1fl  标本审核建议 Re-exam  前白蛋白 132↓mg/L  丙氨酸氨基转移酶 26IU/L  天门冬氨酸氨基转移酶 26IU/L  碱性磷酸酶 196↑IU/L  γ-谷氨酰基转移酶 67↑IU/L  总胆红素 7.5μmol/L  直接胆红素 1.0μmol/L  总蛋白 62g/L  白蛋白 26↓g/L  白球比例 0.72↓  胆汁酸 34.3↑μmol/L  尿素 4.2mmol/L  肌酐 48↓μmol/L  尿酸 219μmol/L  钠 136mmol/L  钾 3.26↓mmol/L  氯 100mmol/L  二氧化碳 23.0mmol/L  钙 1.99↓mmol/L  磷 0.93mmol/L  估算肾小球滤过率 115.5ml/min/1.73m2  甲胎蛋白 6.00ng/mL  癌胚抗原 13.73↑ng/mL  神经元特异性烯醇化酶 9.90ng/mL  细胞角蛋白19 2.17↑ng/mL  鳞状细胞癌相关抗原 0.90ng/mL  糖类抗原125 11.9U/mL  糖类抗原724 >300.00↑U/mL  糖类抗原199 107.4↑U/mL  糖类抗原242 6.9U/mL  糖类抗原153 5.4U/mL  总前列腺特异性抗原 0.221ng/mL  游离前列腺特异性抗原 0.136ng/mL  游离/总前列腺特异性抗原 0.62",
        "出院时情况": "一般情况可",
        "病程与治疗情况": "患者入院后完善各项检查，排除禁忌，于2020-3-31行白蛋白紫杉醇 300mg + 奥沙利铂 185mg + 替吉奥 3# bid d1-14治疗， 并止吐、护胃等治疗，现一般情况可，请示主任医师后，予出院",
        "出院后用药建议": "1、注意休息及营养。        2、出院后一周复查血常规，若WBC小于3*10-9/L，或NE小于1.5*10-9/L，予以升白治疗。 3、胃肠肿瘤专病门诊随访。",
        "病人信息": {
            "姓名": "测试病人0279",
            "性别": "男",
            "科室": "肿瘤科一病区",
            "床号": "8551",
            "住院号": "z83531",
            "住院流水号": "20033100000240",
            "年龄": "58",
            "出生年月": "1962-03-04",
            "入院时间": "2020-04-02",
            "出院时间": ""
        }
    }
}