{
    "19062600000160": {
        "基本信息": {
            "出院诊断": "帕金森病",
            "床号": "8551",
            "科别": "功能神外病区",
            "入院时间": "2019-06-26 10:10",
            "出院时间": "2019-07-03 10:00",
            "姓名": "测试病人0279",
            "性别": "女",
            "年龄": "69",
            "住院号": "z83531",
            "入院诊断": "帕金森病"
        },
        "入院时简要病史": "患者因“四肢震颤、僵直7年”入院。患者7年前无明显诱因下出现双下肢不自主抖动，静止时出现，紧张时加重，前往当地医院就诊，考虑帕金森病，口服美多芭1/4片治疗有效，后症状进展，逐渐增加药量，近1年来患者出现四肢僵硬，行动缓慢，起步、翻身困难，行走困难，会突然动不了，现口服“美多芭1片 3次/日，森福罗 1片 3次/日”，药物有效时间越来越短，为求进一步治疗，前来我院。病程中神志清楚，精神尚可，睡眠、饮食尚可，便秘，体重未见明确增减。                         ",
        "体检摘要": "神志清楚，精神尚可，双侧瞳孔等大等圆，直径3mm，直接、间接对光反射灵敏，四肢肌力正常，肌TM员工名称TM齿轮样增高，伴震颤，指鼻试验能完成，后拉试验可恢复。",
        "生命体征": {
            "T": "36.9",
            "P": "72",
            "R": "17",
            "BP高": "165",
            "BP低": "76"
        },
        "住院期间医疗情况": "【血常规】白细胞计数 5.98x10^9/L  中性粒细胞% 79.8↑％  淋巴细胞% 14.9↓％  单核细胞% 4.5％  嗜酸性粒细胞% 0.6％  嗜碱性粒细胞% 0.2％  中性粒细胞计数 4.77×10^9/L  淋巴细胞计数 0.89×10^9/L  单核细胞计数 0.27×10^9/L  嗜酸性粒细胞计数 0.04×10^9/L  嗜碱性粒细胞计数 0.01×10^9/L  红细胞计数 4.59×10^12/L  血红蛋白 136g/L  红细胞比容 0.414  平均红细胞体积 90.2fl  平均血红蛋白量 29.8pg  平均血红蛋白浓度 330g/L  红细胞分布宽度 12.9％  血小板计数 185×10^9/L  血小板平均体积 10.4fl 【生化】  葡萄糖 5.29mmol/L  丙氨酸氨基转移酶 9↓IU/L  天门冬氨酸氨基转移酶 20IU/L  碱性磷酸酶 91IU/L  γ-谷氨酰基转移酶 15IU/L  总胆红素 8.5μmol/L  直接胆红素 1.3μmol/L  总蛋白 76g/L  白蛋白 44g/L  白球比例 1.38  尿素 7.4↑mmol/L  肌酐 58μmol/L  尿酸 221μmol/L  钠 143mmol/L  钾 3.90mmol/L  氯 104mmol/L  二氧化碳 23.1mmol/L  钙 2.34mmol/L  磷 1.17mmol/L  估算肾小球滤过率 90.6ml/min/1.73m2 【DIC】  APTT 28.4秒  PT 10.8秒  INR 0.91  TT 18.70秒  Fg 2.4g/L  纤维蛋白降解产物 2.5mg/L  D-二聚体定量 0.26mg/L 【免疫】  抗梅毒螺旋体抗体 0.07  梅毒螺旋体RPR 阴性(-) 【病毒】  乙肝病毒表面抗原 0.00(-)IU/mL  乙肝病毒表面抗体 1.26(-)mIU/mL  乙肝病毒e抗原 0.459(-)  乙肝病毒e抗体 1.77(-)  乙肝病毒核心抗体 0.14(-)  乙肝病毒核心抗体IgM 0.11(-) 2019-06-26 胸部-XRAY：两肺纹理增多稍乱模糊；心脏稍大，主动脉迂曲伴壁钙化；请结合临床、病史及其他检查，随访。 2019-06-26 头颅-MR：脑部MR增强术前定位，请结合临床病史及相关检查、随访，必要时建议常规头颅MR检查。  2019-06-26 头颅-MR：双侧基底节区、侧脑室旁及额顶叶白质内见多发斑片状异常信号灶，T2W呈高信号。余颅脑内未见明显异常信号及异常强化灶。各脑室、脑池及脑沟略增宽、扩大。中线结构无移位。双侧副鼻窦区未见明显异常。脑部MR增强术前定位，请结合临床病史及相关检查、随访，必要时建议常规头颅MR检查。  2019-06-26 头颅-CT：功能神外术前定位，请结合临床及其它检查，随访 2019-7-1 头颅-CT：头颅定位术后改变。请结合临床，随访。  ",
        "出院时情况": "神清精神可，一般状况可。皮肤切口愈合良好，开机后僵硬震颤控制满意。",
        "病程与治疗情况": "患者入院后完善术前检查、明确诊断后于2019-6-28行全麻下立体定向双侧脑深部电极植入术，术顺安返。术后予以对症支持治疗，观察临时刺激效果满意后于2019-7-1行全麻下刺激器植入术，术顺安返。术后予以护胃化痰、止血抗炎、营养神经等对症支持治疗。现患者恢复可，予以出院。",
        "出院后用药建议": "1、注意营养与休息，功能神经外科门诊随访; 2、2周后拆线，1月后返院程控（自行预约功能神经外科帕金森专病门诊或疑难程控门诊）； 3、患者为电极植入术后，可安全乘坐飞机、火车、汽车等交通工具。",
        "病人信息": {
            "姓名": "测试病人0279",
            "性别": "女",
            "科室": "功能神外病区",
            "床号": "8551",
            "住院号": "z83531",
            "住院流水号": "19062600000160",
            "年龄": "69",
            "出生年月": "1949-12-03",
            "入院时间": "2019-07-03",
            "出院时间": ""
        }
    }
}