{
  "19020500000023": {
    "基本信息": {
      "出院诊断": "支气管肺炎,心肌损害",
      "床号": "13",
      "科别": "儿科病区",
      "入院时间": "2019-02-05",
      "出院时间": "无法判断",
      "姓名": "测试病人2345",
      "性别": "女",
      "年龄": "3",
      "住院号": "z1495",
      "入院诊断": "支气管肺炎"
    },
    "入院时简要病史": "患儿发热三天，热峰39~40℃，伴咳嗽，有痰音，无抽搐，无口唇发绀，无腹痛腹泻等。",
    "体检摘要": "神清，精神可，全身皮肤黏膜无苍白黄染，无色素沉着，外周淋巴结未及肿大，咽红，双侧扁桃体I°肿大，颈软，气管居中，双肺呼吸音粗，可闻及明显粗湿啰音，心音有力，心律齐，未闻及明显心脏杂音，腹软，无压痛及反跳痛，肝脾肋下未及，肠鸣音无亢进，四肢、脊柱无畸形。",
    "生命体征": {
      "T": "36.8",
      "P": "85",
      "R": "22",
      "BP高": "120",
      "BP低": "85"
    },
    "住院期间医疗情况": "over_length",
    "出院时情况": "神清，精神可，一般状况可。",
    "病程与治疗情况": "患儿入院后完善相关检查，予以头孢呋辛、罗氏芬抗感染治疗，氨溴索化痰止咳，磷酸肌酸钠营养心肌等治疗，雾化吸入治疗，病情好转，经上级医师查房后同意，予以出院。",
    "出院后用药建议": "1、注意休息，避免感染； 2、出院带药： 仙特明滴剂（50mg/支，1支，口服，每天1次，每次半支） 顺尔宁颗粒（4mg/袋，1袋，口服，每晚1次，每次1袋） 橘红痰咳液（10ml/支，口服，每天3次，每次1支） 3、门诊随访，如有不适，及时就诊。",
    "病人信息": {
      "姓名": "测试病人2345",
      "性别": "女",
      "科室": "儿科病区",
      "床号": "13",
      "住院号": "z1495",
      "住院流水号": "19020500000023",
      "年龄": "3",
      "出生年月": "",
      "入院时间": "2019-02-05",
      "出院时间": "无法判断"
    }
  }
}