{
  "19033000000148": {
    "患者基本信息": "###科室类别:\n小儿科\n\n###入院相关诊断:\n诊断时间:2019-03-30\n诊断类型:入院诊断\n诊断名称:社区获得性肺炎，非重症\n\n###告未成年患者监护人书:\n时间:2019-03-30\n患者信息:姓名:万梅 性别:女 年龄:8 入院日期:2019.03.30 12:8 病区名称:儿科病区 床号:13 住院号:zyh456440\n###新入院评估单:\n时间:2019-03-30\n三、生理状况评估:体温 37.2 ℃，脉搏 112 次/分，呼吸 22 次/分，血压 106 /68 mmHg 意识及感知觉状况评估: 清醒 ，感知觉未受损（对指令有反应，能准确表达疼痛和不适） 语言表达: 清楚 ，对答切题 视力: 正常 听力: 正常\n###首次病程记录:\n时间:2019-03-30\n初步诊断:社区获得性肺炎，非重症\n###入院记录:\n时间:2019-03-30\n初步诊断:社区获得性肺炎，非重症\n\n###出院医嘱:\n医嘱时间:2019-04-12\n医嘱类型名称:临时医嘱\t医嘱类型:文字医嘱\t医嘱项类别:文字医嘱\t医嘱项名称:出院\t单次剂量数量:1.0\t单次给药数量:1.0\t给药频次:ONCE\n请根据所给患者的医疗文书，生成该患者出院小结文书中的“患者基本信息”字段内容。输出要求为标准json格式，包含字段“住院号”，“床号”，“入院时间”，“出院时间”，“科别”，“科室”，“姓名”，“年龄”，“性别”，“低压(BP低)”，“高压(BP高)”，“脉搏(P)”，“呼吸(R)”，“体温(T)”以及“入院诊断”。\n字段介绍:对给定文本进行处理，抽取所需的关键字段",
    "出院诊断": "###科室类别:\n小儿科\n\n###出院相关诊断:\n诊断时间:2019-04-12\n诊断类型:出院诊断\n诊断名称:社区获得性肺炎，非重症\n\n诊断时间:2019-04-12\n诊断类型:出院诊断(补充)\n诊断名称:心肌损害\n\n###主治医师日常查房记录:\n时间:2019-04-12\nTM员工名称TM 主治医生查房:对病情的分析: 目前患儿偶有咳嗽，不剧，无发热、咳痰，无鼻塞、流涕等不适，一般情况可。 查体:神清，精神可，全身皮肤粘膜无苍白黄染，咽稍红，扁桃体I°大，未见渗出，颈软，气管居中，胸廓无畸形，双肺呼吸音粗，未闻及干湿啰音，心律齐，未及明显心脏杂音，腹软无压痛及反跳痛，肠鸣音无亢进，肝脾肋下未及，四肢无畸形，双下肢无水肿，NS（-）。 诊疗意见: 患儿目前一般情况可，明日予以带药出院。\n\n###最后一个在院评估单:\n###在院评估单:\n时间:2019-04-12\n基础评估:1.生活自理能力评估: Barthel指数总分85分。2.活动能力评估: 步态稳定 ；活动状态:活动自如 。 3.意识状况评估:神志: 清醒 ，感知觉未受损（对指令有反应，能准确表达疼痛和不适） 。 4.粘膜与皮肤状况评估:颜色: 正常 ；温度: 正常 ；湿度: 正常（皮肤经常保持干燥，只需常规更换床单） ；皮肤完整性: 完整 。 无 水肿 ；无 静脉炎 ；无 瘙痒；无 麻木；无 灼烧感 。5.疼痛: 无 疼痛 。 6.排泄: 无 失禁 。 7.意外事件评估: 未发生意外事件。 患者昨夜睡眠: 正常 营养状况评估:良好(饮食摄入和平时一样，每餐有蛋白质摄入) ，无营养支持。 危重症程度评估: 无 严重器官系统功能不全。 无 免疫损害。 格拉斯评分: 15分 。 危重症评分: 6分 。 高危因素的筛查 该病人目前不存在跌倒风险 该病人目前不存在压疮风险。 分级护理级别: 该病人分级护理建议为三级护理。\n置管状态:无置管。 【医学元素\\签名\\护士签名2-护理评估】 【医学元素\\签名\\护士签名3-护理评估】\n根据提供的患者医疗记录，为其出院小结的“出院诊断”部分生成内容。使用文本格式输出。\n字段介绍:分析患者的诊断和病程记录，输出出院诊断信息，确保使用标准诊断术语，若需要注明相关的描述信息，在括号内说明。",
    "入院时简要病史": "###科室类别:\n小儿科\n\n###首次病程记录:\n时间:2019-03-30\n病例特点:1、患儿，女，8岁 2、主诉:发热伴咳嗽4天 3、现病史:患儿4天前（3.26）无明显诱因下出现发热，体温最高39℃，家长自行予口服退热药（具体不详）后可退至38℃，热程4-6小时，伴少许咳嗽，无痰，无咽痛，无腹痛腹泻，无喘息气促，无发绀青紫，无皮疹，无抽搐，就诊我院急诊，查甲乙流阴性，血常规+CRP示CRP 14mg/L， WBC 8.85*10^9/L,，N% 75.8%，HB 133g/L， PLT 212*10^9/L，予头孢克洛口服、 金振口服液止咳对症治疗。口服用药后症状无明显改善，仍有反复发热，伴咳嗽。昨日起咳嗽加重，有痰，痰呈黄色粘痰，无鼻塞流涕，无咽痛，无头晕头痛，无喘息，无恶心呕吐，无肌肉酸痛等不适。今日再次至我院急诊就诊，复查甲乙流阴性，血常规+CRP示CRP 24mg/L, WBC 6.91*10^9/L，N% 74.7%，查胸片示左肺纹理增多模糊，左侧肺门影增大，左肺斑片渗出影，感染？左侧少许胸腔积液可能。现为进一步诊治，急诊拟“支气管肺炎”收入院。 病来，患儿神清，精神可，胃纳一般，二便无明显异常，体重未见明显增减。 4、查体:神清，精神可，查体合作，全身皮肤粘膜无苍白黄染，咽稍红，扁桃体I°大，未见渗出，颈软，气管居中，胸廓无畸形，双肺呼吸音粗，未闻及干湿啰音，左下肺呼吸音稍低，心率112次/分，心律齐，未及明显心脏杂音，腹软无压痛及反跳痛，肠鸣音无亢进，肝脾肋下未及，四肢无畸形，双下肢无水肿，NS（-）。 5、辅检:我院 2019.3.27【甲乙流】阴性，【血常规+CRP】CRP14mg/L, WBC 8.85*10^9/L, N% 75.8%, HB 133g/L, PLT 212*10^9/L, 2019.3.30【甲乙流】阴性，【血常规+CRP】CRP24mg/L, WBC 6.91*10^9/L, N% 74.7%, HB 129 g/L, PLT 193*10^9/L, 【胸片】 左肺纹理增多模糊，左侧肺门影增大，左肺斑片渗出影，感染？左侧少许胸腔积液可能\n请根据上述患者资料，撰写出院小结中“入院时简要病史”字段。输出应为一段文本。\n字段介绍:检查患者的病例文书，抽取相关字段信息，整理其入院时的简要病史，具体的报告内容不做修改。",
    "体检摘要": "###科室类别:\n小儿科\n\n###首次病程记录:\n时间:2019-03-30\n病例特点:1、患儿，女，8岁 2、主诉:发热伴咳嗽4天 3、现病史:患儿4天前（3.26）无明显诱因下出现发热，体温最高39℃，家长自行予口服退热药（具体不详）后可退至38℃，热程4-6小时，伴少许咳嗽，无痰，无咽痛，无腹痛腹泻，无喘息气促，无发绀青紫，无皮疹，无抽搐，就诊我院急诊，查甲乙流阴性，血常规+CRP示CRP 14mg/L， WBC 8.85*10^9/L,，N% 75.8%，HB 133g/L， PLT 212*10^9/L，予头孢克洛口服、 金振口服液止咳对症治疗。口服用药后症状无明显改善，仍有反复发热，伴咳嗽。昨日起咳嗽加重，有痰，痰呈黄色粘痰，无鼻塞流涕，无咽痛，无头晕头痛，无喘息，无恶心呕吐，无肌肉酸痛等不适。今日再次至我院急诊就诊，复查甲乙流阴性，血常规+CRP示CRP 24mg/L, WBC 6.91*10^9/L，N% 74.7%，查胸片示左肺纹理增多模糊，左侧肺门影增大，左肺斑片渗出影，感染？左侧少许胸腔积液可能。现为进一步诊治，急诊拟“支气管肺炎”收入院。 病来，患儿神清，精神可，胃纳一般，二便无明显异常，体重未见明显增减。 4、查体:神清，精神可，查体合作，全身皮肤粘膜无苍白黄染，咽稍红，扁桃体I°大，未见渗出，颈软，气管居中，胸廓无畸形，双肺呼吸音粗，未闻及干湿啰音，左下肺呼吸音稍低，心率112次/分，心律齐，未及明显心脏杂音，腹软无压痛及反跳痛，肠鸣音无亢进，肝脾肋下未及，四肢无畸形，双下肢无水肿，NS（-）。 5、辅检:我院 2019.3.27【甲乙流】阴性，【血常规+CRP】CRP14mg/L, WBC 8.85*10^9/L, N% 75.8%, HB 133g/L, PLT 212*10^9/L, 2019.3.30【甲乙流】阴性，【血常规+CRP】CRP24mg/L, WBC 6.91*10^9/L, N% 74.7%, HB 129 g/L, PLT 193*10^9/L, 【胸片】 左肺纹理增多模糊，左侧肺门影增大，左肺斑片渗出影，感染？左侧少许胸腔积液可能\n根据患者医疗文书，为出院小结的“体检摘要”部分编写内容。确保输出为一段文本。\n字段介绍:检查患者的病例文书，提取所需的关键字段信息，归纳患者的体检摘要，详细的报告内容和描述不要修改。",
    "住院期间医疗情况": "###科室类别:\n小儿科\n\n###检查:\n检查ID:2019033100000116|1\n报告时间:2019-04-01 15:13:40\n描述:放射|平扫|住院CT|胸部CT(薄层) 平扫\n图像所见:左肺见散在斑片状高密度影，境界模糊不清，右肺亦显示少许斑片状渗出。 两肺门区未见异常。 所示气管支气管影正常。 纵隔内未见异常增大的淋巴结。\n图像分析:两肺炎症，左肺明显。请结合临床及其他相关检查，随诊。\n\n检查ID:2019041010001846|1\n报告时间:2019-04-10 14:09:28\n描述:放射|胸部|X-ray平片|胸部 胸部\n图像所见:所示胸廓骨骼及胸壁软组织未见异常。 纵隔及气管居中未见移位。 纵隔未见增宽。 心脏形态大小未见异常。 两膈光整，两肋膈角锐利。 左肺门饱满，右肺门形态大小位置未见异常。 两肺纹理略增多。左肺下野小斑片影。\n图像分析:左下肺炎症，较2019-03-30前片略吸收，请结合临床及其他相关检查。\n\n###检验:\n报告时间:2019-03-30 13:44:48\n检验详情:APTT:35.3秒,正常(22.3—38.7秒);\tD-二聚体定量:0.86mg/L,偏高(0.0—0.55mg/L);\t纤维蛋白降解产物:2.5mg/L,正常(0.0—5.0mg/L);\tFg:5.3g/L,偏高(1.8—3.5g/L);\tTT:17.00秒,正常(14.0—21.0秒);\tINR:1.09,未判断(0.0—0.0);\tPT:12.8秒,正常(10.0—16.0秒);\n\n报告时间:2019-03-30 13:54:17\n检验详情:肌酸激酶:352IU/L,偏高(22.0—269.0IU/L);\t尿素:3.2mmol/L,正常(2.5—7.1mmol/L);\t钙:2.33mmol/L,正常(2.0—2.75mmol/L);\t氯:96mmol/L,正常(96.0—108.0mmol/L);\t二氧化碳:23.3mmol/L,正常(21.0—31.0mmol/L);\t肌酐:43μmol/L,偏低(53.0—97.0μmol/L);\t肌钙蛋白I:0.01ng/mL,正常(0.0—0.04ng/mL);\t直接胆红素:1.9μmol/L,正常(0.0—6.8μmol/L);\t葡萄糖:5.83mmol/L,正常(3.9—6.1mmol/L);\t碱性磷酸酶:175IU/L,偏高(38.0—126.0IU/L);\t前白蛋白:120mg/L,偏低(180.0—380.0mg/L);\t白球比例:1.17,偏低(1.25—2.5);\t白蛋白:41g/L,正常(35.0—55.0g/L);\t天门冬氨酸氨基转移酶:43IU/L,偏高(8.0—40.0IU/L);\tCK-MB质量:1.0ng/mL,正常(0.3—4.0ng/mL);\t磷:1.48mmol/L,正常(0.8—1.6mmol/L);\t钠:133mmol/L,正常(130.0—147.0mmol/L);\t乳酸脱氢酶:338IU/L,偏高(98.0—192.0IU/L);\t钾:4.00mmol/L,正常(3.5—5.1mmol/L);\t总胆红素:10.4μmol/L,正常(4.7—24.0μmol/L);\t总蛋白:76g/L,正常(60.0—83.0g/L);\t估算肾小球滤过率:153.4ml/min/1.73m2,未判断(0.0—0.0ml/min/1.73m2);\t胆汁酸:8.5μmol/L,正常(0.1—10.0μmol/L);\t肌红蛋白定量:13.9ng/mL,正常(0.0—70.0ng/mL);\tγ-谷氨酰基转移酶:16IU/L,正常(7.0—64.0IU/L);\t丙氨酸氨基转移酶:29IU/L,正常(10.0—64.0IU/L);\t尿酸:177μmol/L,正常(160.0—430.0μmol/L);\n\n报告时间:2019-03-30 15:28:24\n检验详情:红细胞沉降率:28mm/h,未判断(0.0—0.0mm/h);\n\n报告时间:2019-03-31 08:22:44\n检验详情:性状:软,未判断(0.0—0.0);\t虫卵:阴性(-),未判断(0.0—0.0);\t白细胞:阴性,未判断(0.0—0.0);\t红细胞:阴性,未判断(0.0—0.0);\t隐血试验:阴性(-),未判断(0.0—0.0);\t颜色:黄色,未判断(0.0—0.0);\n\n报告时间:2019-03-31 08:55:55\n检验详情:上皮细胞(镜检):0/HP,未判断(0.0—0.0/HP);\t白细胞(镜检):0/HP,未判断(0.0—0.0/HP);\t亚硝酸盐:阴性(-),正常(0.0—0.0);\t酮体:阳性(+),偏高(0.0—0.0);\t葡萄糖:阴性(-),正常(0.0—0.0);\t潜血:阴性(-),正常(0.0—0.0);\t白细胞:阴性(-),正常(0.0—0.0);\t红细胞(镜检):0/HP,未判断(0.0—0.0/HP);\t结晶(镜检):阴性(-),未判断(0.0—0.0);\t管型(镜检):0/LP,正常(0.0—1.0/LP);\t尿胆元:阴性(-),正常(0.0—0.0);\t胆红素:阴性(-),正常(0.0—0.0);\t蛋白质:阴性(-),正常(0.0—0.0);\t酸碱度:6.0,正常(5.0—9.0);\t比重:1.006,正常(1.005—1.03);\n\n报告时间:2019-04-01 12:31:10\n检验详情:EB病毒EAIgG:<5.00U/mL,正常(-9999.0—10.0U/mL);\t抗巨细胞病毒IgG:115.60,偏高(-9999.0—6.0);\t抗巨细胞病毒IgM:0.26,正常(-9999.0—0.85);\t降钙素原:0.08ng/mL,正常(0.0—0.5ng/mL);\tEB病毒EBNAIgG:325.00U/mL,偏高(-9999.0—5.0U/mL);\tEB病毒EBVIgM:11.90,正常(0.0—20.0);\tEB病毒VCAIgG:93.20U/mL,偏高(-9999.0—20.0U/mL);\n\n报告时间:2019-04-02 08:44:32\n检验详情:EB病毒:＜5.0×10^2copies/ml,未判断(-10000.0—99999.0copies/ml);\t肺炎支原体:<1.0×10^3copies/ml,未判断(-10000.0—99999.0copies/ml);\n\n报告时间:2019-04-02 09:57:50\n检验详情:红细胞计数:4.38×10^12/L,正常(3.68—5.13×10^12/L);\t血红蛋白:129g/L,正常(113.0—151.0g/L);\t单核细胞计数:0.31×10^9/L,正常(0.12—1.0×10^9/L);\t血小板平均体积:8.6fl,正常(6.5—12.0fl);\t嗜碱性粒细胞计数:0.02×10^9/L,正常(0.0—1.0×10^9/L);\t嗜酸性粒细胞计数:0.11×10^9/L,正常(0.02—0.5×10^9/L);\t单核细胞%:7.0％,正常(3.0—10.0％);\t淋巴细胞%:27.1％,正常(20.0—40.0％);\t中性粒细胞%:62.9％,正常(50.0—70.0％);\t平均血红蛋白浓度:335g/L,正常(322.0—362.0g/L);\t红细胞分布宽度:12.1％,正常(11.6—14.0％);\t血小板计数:257×10^9/L,正常(101.0—320.0×10^9/L);\t淋巴细胞计数:1.21×10^9/L,正常(0.8—4.0×10^9/L);\t白细胞计数:4.47×10^9/L,正常(3.69—9.16×10^9/L);\t嗜酸性粒细胞%:2.5％,正常(0.5—5.0％);\t嗜碱性粒细胞%:0.5％,正常(0.0—1.0％);\t中性粒细胞计数:2.82×10^9/L,正常(2.0—7.0×10^9/L);\tC-反应蛋白:19.5mg/L,偏高(0.0—10.0mg/L);\t红细胞比容:0.385,正常(0.335—0.45);\t平均红细胞体积:88.0fl,正常(82.6—99.1fl);\t平均血红蛋白量:29.5pg,正常(26.9—33.3pg);\n\n报告时间:2019-04-02 14:06:53\n检验详情:LP:阴性(-),未判断(0.0—0.0);\tCP:阴性(-),未判断(0.0—0.0);\tMP:阳性(+),未判断(0.0—0.0);\n\n报告时间:2019-04-02 15:03:12\n检验详情:抗副流1,2,3型IgM:阴性(-),正常(0.0—-1.0);\t抗军团菌1型IgM:阴性(-),正常(0.0—-1.0);\t抗Q热立克次体IgM:阴性(-),正常(0.0—-1.0);\t抗肺炎衣原体IgM:阴性(-),正常(0.0—-1.0);\t抗腺病毒IgM:阴性(-),正常(0.0—-1.0);\t肺支抗体:阴性(-),正常(0.0—-1.0);\t抗R合胞病毒IgM:阴性(-),正常(0.0—-1.0);\t抗甲流病毒IgM:阴性(-),正常(0.0—-1.0);\t抗乙流病毒IgM:阴性(-),正常(0.0—-1.0);\n\n报告时间:2019-04-02 15:03:13\n检验详情:肺支抗体:阴性(-),正常(0.0—-1.0);\n\n报告时间:2019-04-02 16:13:48\n检验详情:促甲状腺素(TSH):1.0763μIU/mL,正常(0.35—4.94μIU/mL);\t三碘甲腺原氨酸(T3):1.84nmol/L,正常(0.89—2.44nmol/L);\t甲状腺素(T4):160.51nmol/L,偏高(62.67—150.84nmol/L);\t甲状腺受体抗体(TRAb):0.36IU/L,正常(0.0—1.75IU/L);\t甲状腺过氧化物酶抗体(TPOAb):0.10IU/mL,正常(0.0—5.61IU/mL);\t甲状腺球蛋白抗体(TGAb):1.26IU/mL,正常(0.0—4.11IU/mL);\t游离甲状腺素(FT4):16.88pmol/L,正常(9.01—19.04pmol/L);\t游离三碘甲腺原氨酸(FT3):4.54pmol/L,正常(2.63—5.7pmol/L);\n\n报告时间:2019-04-04 15:58:30\n检验详情:培养五天细菌真菌厌氧菌未生长:,未判断(0.0—0.0);\n\n报告时间:2019-04-04 15:58:31\n检验详情:培养五天细菌真菌厌氧菌未生长:,未判断(0.0—0.0);\n\n报告时间:2019-04-11 08:24:21\n检验详情:CK-MB质量:1.2ng/mL,正常(0.3—4.0ng/mL);\t肌红蛋白定量:7.2ng/mL,正常(0.0—70.0ng/mL);\t乳酸脱氢酶:282IU/L,偏高(98.0—192.0IU/L);\t肌钙蛋白I:0.01ng/mL,正常(0.0—0.04ng/mL);\t肌酸激酶:65IU/L,正常(22.0—269.0IU/L);\t天门冬氨酸氨基转移酶:35IU/L,正常(8.0—40.0IU/L);\n\n报告时间:2019-04-11 08:36:09\n检验详情:嗜碱性粒细胞%:0.4％,正常(0.0—1.0％);\t中性粒细胞计数:3.73×10^9/L,正常(2.0—7.0×10^9/L);\t平均红细胞体积:88.9fl,正常(82.6—99.1fl);\t嗜酸性粒细胞计数:0.19×10^9/L,正常(0.02—0.5×10^9/L);\t嗜碱性粒细胞计数:0.03×10^9/L,正常(0.0—1.0×10^9/L);\t红细胞计数:4.52×10^12/L,正常(3.68—5.13×10^12/L);\t血红蛋白:133g/L,正常(113.0—151.0g/L);\t红细胞比容:0.402,正常(0.335—0.45);\t平均血红蛋白量:29.4pg,正常(26.9—33.3pg);\t血小板平均体积:7.9fl,正常(6.5—12.0fl);\t平均血红蛋白浓度:331g/L,正常(322.0—362.0g/L);\t红细胞分布宽度:12.6％,正常(11.6—14.0％);\t血小板计数:477×10^9/L,偏高(101.0—320.0×10^9/L);\t标本审核建议:Auto Validation OK,未判断(0.0—0.0);\tC反应蛋白:5mg/L,正常(0.0—10.0mg/L);\t仪器名称:BC6800_1,未判断(0.0—0.0);\t中性粒细胞%:49.0％,偏低(50.0—70.0％);\t单核细胞计数:0.40×10^9/L,正常(0.12—1.0×10^9/L);\t淋巴细胞计数:3.27×10^9/L,正常(0.8—4.0×10^9/L);\t嗜酸性粒细胞%:2.5％,正常(0.5—5.0％);\t淋巴细胞%:42.9％,偏高(20.0—40.0％);\t白细胞计数:7.62x10^9/L,正常(3.69—9.16x10^9/L);\t单核细胞%:5.2％,正常(3.0—10.0％);\n\n###日常病程辅检:\n无\n\n###主任医师首次查房记录:\n时间:2019-04-01\n补充病史与体征:患儿今日仍有发热，体温高达39℃，伴咳嗽，无呕吐，无腹泻。 查体:神志清，精神可，查体合作，全身皮肤粘膜无苍白黄染，咽稍红，扁桃体I°大，未见渗出，颈软，气管居中，胸廓无畸形，双肺呼吸音粗，左肺可及湿罗音，左下肺呼吸音稍低，心率110次/分，心律齐，未及明显心脏杂音，腹软无压痛及反跳痛，肠鸣音无亢进，肝脾肋下未及，四肢无畸形，双下肢无水肿，NS（-）。 辅助检查:【血生化】肌酸激酶 352↑IU/L 白蛋白 41g/L 钾 4.00mmol/L 天门冬氨酸氨基转移酶 43↑IU/L 乳酸脱氢酶 338↑IU/L CK-MB质量1.0ng/mL 肌红蛋白定量13.9ng/mL 肌钙蛋白I 0.01ng/mL； 【尿常规】未见异常 【红细胞沉降率】 28mm/h 【病原体检测】降钙素原 0.08ng/mL 抗巨细胞病毒IgG 115.60↑ 抗巨细胞病毒IgM 0.26 EB病毒EAIgG <5.00U/mL EB病毒EBVIgM 11.90 EB病毒VCAIgG 93.20↑U/mL EB病毒EBNAIgG 325.00↑U/mL。\n###主治医师首次查房记录:\n时间:2019-03-31\nTM员工名称TM 主治医生查房:补充的病史和体征: 患儿 昨日仍有发热，最高体温38.5℃，予以美林退热，伴咳嗽、咳痰，无呕吐、腹泻。 神清，精神可，查体合作，全身皮肤粘膜无苍白黄染，咽稍红，扁桃体I°大，未见渗出，颈软，气管居中，胸廓无畸形，双肺呼吸音粗，未闻及干湿啰音，左下肺呼吸音稍低，心率112次/分，心律齐，未及明显心脏杂音，腹软无压痛及反跳痛，肠鸣音无亢进，肝脾肋下未及，四肢无畸形，双下肢无水肿，NS（-） 辅助检查:【DIC】APTT 35.3秒 PT 12.8秒 INR 1.09 TT 17.00秒 Fg 5.3↑g/L 纤维蛋白降解产物 2.5mg/L D-二聚体定量 0.86↑mg/L 【血生化】葡萄糖 5.83mmol/L 丙氨酸氨基转移酶 29IU/L 白蛋白 41g/L 钾 4.00mmol/L 钙 2.33mmol/L 【ESR】红细胞沉降率 28mm/h 颜色 【粪常规】黄色 性状 软 红细胞 阴性 白细胞 阴性 隐血试验 阴性(-) 虫卵 阴性(-) 【尿常规】白细胞 阴性(-) 蛋白质 阴性(-) 潜血 阴性(-) 诊断依据与鉴别诊断的分析:\n根据患者的医疗材料，制作出院小结文档里的“住院期间医疗情况”部分内容。请以文本格式输出。\n字段介绍:从输入中识别并选择该患者住院期间的关键检验检查信息，具体报告内容不用进行摘要和修改。",
    "病程与治疗情况": "###科室类别:\n小儿科\n\n###首次病程记录:\n时间:2019-03-30\n诊疗计划:1、入院后完善相关常规检查、病原学检查、心电图评估患儿病情及明确诊断； 2、予阿奇霉素抗感染，沐舒坦化痰，雾化吸入等对症治疗。\n病例特点:1、患儿，女，8岁 2、主诉:发热伴咳嗽4天 3、现病史:患儿4天前（3.26）无明显诱因下出现发热，体温最高39℃，家长自行予口服退热药（具体不详）后可退至38℃，热程4-6小时，伴少许咳嗽，无痰，无咽痛，无腹痛腹泻，无喘息气促，无发绀青紫，无皮疹，无抽搐，就诊我院急诊，查甲乙流阴性，血常规+CRP示CRP 14mg/L， WBC 8.85*10^9/L,，N% 75.8%，HB 133g/L， PLT 212*10^9/L，予头孢克洛口服、 金振口服液止咳对症治疗。口服用药后症状无明显改善，仍有反复发热，伴咳嗽。昨日起咳嗽加重，有痰，痰呈黄色粘痰，无鼻塞流涕，无咽痛，无头晕头痛，无喘息，无恶心呕吐，无肌肉酸痛等不适。今日再次至我院急诊就诊，复查甲乙流阴性，血常规+CRP示CRP 24mg/L, WBC 6.91*10^9/L，N% 74.7%，查胸片示左肺纹理增多模糊，左侧肺门影增大，左肺斑片渗出影，感染？左侧少许胸腔积液可能。现为进一步诊治，急诊拟“支气管肺炎”收入院。 病来，患儿神清，精神可，胃纳一般，二便无明显异常，体重未见明显增减。 4、查体:神清，精神可，查体合作，全身皮肤粘膜无苍白黄染，咽稍红，扁桃体I°大，未见渗出，颈软，气管居中，胸廓无畸形，双肺呼吸音粗，未闻及干湿啰音，左下肺呼吸音稍低，心率112次/分，心律齐，未及明显心脏杂音，腹软无压痛及反跳痛，肠鸣音无亢进，肝脾肋下未及，四肢无畸形，双下肢无水肿，NS（-）。 5、辅检:我院 2019.3.27【甲乙流】阴性，【血常规+CRP】CRP14mg/L, WBC 8.85*10^9/L, N% 75.8%, HB 133g/L, PLT 212*10^9/L, 2019.3.30【甲乙流】阴性，【血常规+CRP】CRP24mg/L, WBC 6.91*10^9/L, N% 74.7%, HB 129 g/L, PLT 193*10^9/L, 【胸片】 左肺纹理增多模糊，左侧肺门影增大，左肺斑片渗出影，感染？左侧少许胸腔积液可能\n###主任医师首次查房记录:\n时间:2019-04-01\n对病情的分析:患儿，女，8岁，因“发热伴咳嗽4天”就诊， 查体左肺呼吸音低，可及湿罗音，结合胸片，明确“肺炎”诊断。社区获得性肺炎在儿童中常见，病原学主要为细菌、支原体、病毒感染为主，该患儿为学龄期儿童，血常规示白细胞未见明显增高，CRP高，考虑支原体感染可能性大，予以阿奇霉素抗感染治疗，并予沐舒坦化痰及雾化等对症治疗，另外，患儿心肌酶升高，考虑肺炎合并心肌损害，今日予以磷酸肌酸营养心肌治疗。\n诊疗意见:1.继续予头孢呋辛及阿奇霉素联合抗感染，予磷酸肌酸营养心肌，沐舒坦化痰及雾化等对症治疗。 2.继观患儿体温、咳嗽等变化，注意病原体、CT检查结果回报。\n###主治医师日常查房记录:\n时间:2019-04-12\nTM员工名称TM 主治医生查房:对病情的分析: 目前患儿偶有咳嗽，不剧，无发热、咳痰，无鼻塞、流涕等不适，一般情况可。 查体:神清，精神可，全身皮肤粘膜无苍白黄染，咽稍红，扁桃体I°大，未见渗出，颈软，气管居中，胸廓无畸形，双肺呼吸音粗，未闻及干湿啰音，心律齐，未及明显心脏杂音，腹软无压痛及反跳痛，肠鸣音无亢进，肝脾肋下未及，四肢无畸形，双下肢无水肿，NS（-）。 诊疗意见: 患儿目前一般情况可，明日予以带药出院。\n\n###检查:\n检查ID:2019033100000116|1\n报告时间:2019-04-01 15:13:40\n描述:放射|平扫|住院CT|胸部CT(薄层) 平扫\n图像所见:左肺见散在斑片状高密度影，境界模糊不清，右肺亦显示少许斑片状渗出。 两肺门区未见异常。 所示气管支气管影正常。 纵隔内未见异常增大的淋巴结。\n图像分析:两肺炎症，左肺明显。请结合临床及其他相关检查，随诊。\n\n检查ID:2019041010001846|1\n报告时间:2019-04-10 14:09:28\n描述:放射|胸部|X-ray平片|胸部 胸部\n图像所见:所示胸廓骨骼及胸壁软组织未见异常。 纵隔及气管居中未见移位。 纵隔未见增宽。 心脏形态大小未见异常。 两膈光整，两肋膈角锐利。 左肺门饱满，右肺门形态大小位置未见异常。 两肺纹理略增多。左肺下野小斑片影。\n图像分析:左下肺炎症，较2019-03-30前片略吸收，请结合临床及其他相关检查。\n\n###检验:\n报告时间:2019-03-30 13:44:48\n检验详情:APTT:35.3秒,正常(22.3—38.7秒);\tD-二聚体定量:0.86mg/L,偏高(0.0—0.55mg/L);\t纤维蛋白降解产物:2.5mg/L,正常(0.0—5.0mg/L);\tFg:5.3g/L,偏高(1.8—3.5g/L);\tTT:17.00秒,正常(14.0—21.0秒);\tINR:1.09,未判断(0.0—0.0);\tPT:12.8秒,正常(10.0—16.0秒);\n\n报告时间:2019-03-30 13:54:17\n检验详情:肌酸激酶:352IU/L,偏高(22.0—269.0IU/L);\t尿素:3.2mmol/L,正常(2.5—7.1mmol/L);\t钙:2.33mmol/L,正常(2.0—2.75mmol/L);\t氯:96mmol/L,正常(96.0—108.0mmol/L);\t二氧化碳:23.3mmol/L,正常(21.0—31.0mmol/L);\t肌酐:43μmol/L,偏低(53.0—97.0μmol/L);\t肌钙蛋白I:0.01ng/mL,正常(0.0—0.04ng/mL);\t直接胆红素:1.9μmol/L,正常(0.0—6.8μmol/L);\t葡萄糖:5.83mmol/L,正常(3.9—6.1mmol/L);\t碱性磷酸酶:175IU/L,偏高(38.0—126.0IU/L);\t前白蛋白:120mg/L,偏低(180.0—380.0mg/L);\t白球比例:1.17,偏低(1.25—2.5);\t白蛋白:41g/L,正常(35.0—55.0g/L);\t天门冬氨酸氨基转移酶:43IU/L,偏高(8.0—40.0IU/L);\tCK-MB质量:1.0ng/mL,正常(0.3—4.0ng/mL);\t磷:1.48mmol/L,正常(0.8—1.6mmol/L);\t钠:133mmol/L,正常(130.0—147.0mmol/L);\t乳酸脱氢酶:338IU/L,偏高(98.0—192.0IU/L);\t钾:4.00mmol/L,正常(3.5—5.1mmol/L);\t总胆红素:10.4μmol/L,正常(4.7—24.0μmol/L);\t总蛋白:76g/L,正常(60.0—83.0g/L);\t估算肾小球滤过率:153.4ml/min/1.73m2,未判断(0.0—0.0ml/min/1.73m2);\t胆汁酸:8.5μmol/L,正常(0.1—10.0μmol/L);\t肌红蛋白定量:13.9ng/mL,正常(0.0—70.0ng/mL);\tγ-谷氨酰基转移酶:16IU/L,正常(7.0—64.0IU/L);\t丙氨酸氨基转移酶:29IU/L,正常(10.0—64.0IU/L);\t尿酸:177μmol/L,正常(160.0—430.0μmol/L);\n\n报告时间:2019-03-30 15:28:24\n检验详情:红细胞沉降率:28mm/h,未判断(0.0—0.0mm/h);\n\n报告时间:2019-03-31 08:22:44\n检验详情:性状:软,未判断(0.0—0.0);\t虫卵:阴性(-),未判断(0.0—0.0);\t白细胞:阴性,未判断(0.0—0.0);\t红细胞:阴性,未判断(0.0—0.0);\t隐血试验:阴性(-),未判断(0.0—0.0);\t颜色:黄色,未判断(0.0—0.0);\n\n报告时间:2019-03-31 08:55:55\n检验详情:上皮细胞(镜检):0/HP,未判断(0.0—0.0/HP);\t白细胞(镜检):0/HP,未判断(0.0—0.0/HP);\t亚硝酸盐:阴性(-),正常(0.0—0.0);\t酮体:阳性(+),偏高(0.0—0.0);\t葡萄糖:阴性(-),正常(0.0—0.0);\t潜血:阴性(-),正常(0.0—0.0);\t白细胞:阴性(-),正常(0.0—0.0);\t红细胞(镜检):0/HP,未判断(0.0—0.0/HP);\t结晶(镜检):阴性(-),未判断(0.0—0.0);\t管型(镜检):0/LP,正常(0.0—1.0/LP);\t尿胆元:阴性(-),正常(0.0—0.0);\t胆红素:阴性(-),正常(0.0—0.0);\t蛋白质:阴性(-),正常(0.0—0.0);\t酸碱度:6.0,正常(5.0—9.0);\t比重:1.006,正常(1.005—1.03);\n\n报告时间:2019-04-01 12:31:10\n检验详情:EB病毒EAIgG:<5.00U/mL,正常(-9999.0—10.0U/mL);\t抗巨细胞病毒IgG:115.60,偏高(-9999.0—6.0);\t抗巨细胞病毒IgM:0.26,正常(-9999.0—0.85);\t降钙素原:0.08ng/mL,正常(0.0—0.5ng/mL);\tEB病毒EBNAIgG:325.00U/mL,偏高(-9999.0—5.0U/mL);\tEB病毒EBVIgM:11.90,正常(0.0—20.0);\tEB病毒VCAIgG:93.20U/mL,偏高(-9999.0—20.0U/mL);\n\n报告时间:2019-04-02 08:44:32\n检验详情:EB病毒:＜5.0×10^2copies/ml,未判断(-10000.0—99999.0copies/ml);\t肺炎支原体:<1.0×10^3copies/ml,未判断(-10000.0—99999.0copies/ml);\n\n报告时间:2019-04-02 09:57:50\n检验详情:红细胞计数:4.38×10^12/L,正常(3.68—5.13×10^12/L);\t血红蛋白:129g/L,正常(113.0—151.0g/L);\t单核细胞计数:0.31×10^9/L,正常(0.12—1.0×10^9/L);\t血小板平均体积:8.6fl,正常(6.5—12.0fl);\t嗜碱性粒细胞计数:0.02×10^9/L,正常(0.0—1.0×10^9/L);\t嗜酸性粒细胞计数:0.11×10^9/L,正常(0.02—0.5×10^9/L);\t单核细胞%:7.0％,正常(3.0—10.0％);\t淋巴细胞%:27.1％,正常(20.0—40.0％);\t中性粒细胞%:62.9％,正常(50.0—70.0％);\t平均血红蛋白浓度:335g/L,正常(322.0—362.0g/L);\t红细胞分布宽度:12.1％,正常(11.6—14.0％);\t血小板计数:257×10^9/L,正常(101.0—320.0×10^9/L);\t淋巴细胞计数:1.21×10^9/L,正常(0.8—4.0×10^9/L);\t白细胞计数:4.47×10^9/L,正常(3.69—9.16×10^9/L);\t嗜酸性粒细胞%:2.5％,正常(0.5—5.0％);\t嗜碱性粒细胞%:0.5％,正常(0.0—1.0％);\t中性粒细胞计数:2.82×10^9/L,正常(2.0—7.0×10^9/L);\tC-反应蛋白:19.5mg/L,偏高(0.0—10.0mg/L);\t红细胞比容:0.385,正常(0.335—0.45);\t平均红细胞体积:88.0fl,正常(82.6—99.1fl);\t平均血红蛋白量:29.5pg,正常(26.9—33.3pg);\n\n报告时间:2019-04-02 14:06:53\n检验详情:LP:阴性(-),未判断(0.0—0.0);\tCP:阴性(-),未判断(0.0—0.0);\tMP:阳性(+),未判断(0.0—0.0);\n\n报告时间:2019-04-02 15:03:12\n检验详情:抗副流1,2,3型IgM:阴性(-),正常(0.0—-1.0);\t抗军团菌1型IgM:阴性(-),正常(0.0—-1.0);\t抗Q热立克次体IgM:阴性(-),正常(0.0—-1.0);\t抗肺炎衣原体IgM:阴性(-),正常(0.0—-1.0);\t抗腺病毒IgM:阴性(-),正常(0.0—-1.0);\t肺支抗体:阴性(-),正常(0.0—-1.0);\t抗R合胞病毒IgM:阴性(-),正常(0.0—-1.0);\t抗甲流病毒IgM:阴性(-),正常(0.0—-1.0);\t抗乙流病毒IgM:阴性(-),正常(0.0—-1.0);\n\n报告时间:2019-04-02 15:03:13\n检验详情:肺支抗体:阴性(-),正常(0.0—-1.0);\n\n报告时间:2019-04-02 16:13:48\n检验详情:促甲状腺素(TSH):1.0763μIU/mL,正常(0.35—4.94μIU/mL);\t三碘甲腺原氨酸(T3):1.84nmol/L,正常(0.89—2.44nmol/L);\t甲状腺素(T4):160.51nmol/L,偏高(62.67—150.84nmol/L);\t甲状腺受体抗体(TRAb):0.36IU/L,正常(0.0—1.75IU/L);\t甲状腺过氧化物酶抗体(TPOAb):0.10IU/mL,正常(0.0—5.61IU/mL);\t甲状腺球蛋白抗体(TGAb):1.26IU/mL,正常(0.0—4.11IU/mL);\t游离甲状腺素(FT4):16.88pmol/L,正常(9.01—19.04pmol/L);\t游离三碘甲腺原氨酸(FT3):4.54pmol/L,正常(2.63—5.7pmol/L);\n\n报告时间:2019-04-04 15:58:30\n检验详情:培养五天细菌真菌厌氧菌未生长:,未判断(0.0—0.0);\n\n报告时间:2019-04-04 15:58:31\n检验详情:培养五天细菌真菌厌氧菌未生长:,未判断(0.0—0.0);\n\n报告时间:2019-04-11 08:24:21\n检验详情:CK-MB质量:1.2ng/mL,正常(0.3—4.0ng/mL);\t肌红蛋白定量:7.2ng/mL,正常(0.0—70.0ng/mL);\t乳酸脱氢酶:282IU/L,偏高(98.0—192.0IU/L);\t肌钙蛋白I:0.01ng/mL,正常(0.0—0.04ng/mL);\t肌酸激酶:65IU/L,正常(22.0—269.0IU/L);\t天门冬氨酸氨基转移酶:35IU/L,正常(8.0—40.0IU/L);\n\n报告时间:2019-04-11 08:36:09\n检验详情:嗜碱性粒细胞%:0.4％,正常(0.0—1.0％);\t中性粒细胞计数:3.73×10^9/L,正常(2.0—7.0×10^9/L);\t平均红细胞体积:88.9fl,正常(82.6—99.1fl);\t嗜酸性粒细胞计数:0.19×10^9/L,正常(0.02—0.5×10^9/L);\t嗜碱性粒细胞计数:0.03×10^9/L,正常(0.0—1.0×10^9/L);\t红细胞计数:4.52×10^12/L,正常(3.68—5.13×10^12/L);\t血红蛋白:133g/L,正常(113.0—151.0g/L);\t红细胞比容:0.402,正常(0.335—0.45);\t平均血红蛋白量:29.4pg,正常(26.9—33.3pg);\t血小板平均体积:7.9fl,正常(6.5—12.0fl);\t平均血红蛋白浓度:331g/L,正常(322.0—362.0g/L);\t红细胞分布宽度:12.6％,正常(11.6—14.0％);\t血小板计数:477×10^9/L,偏高(101.0—320.0×10^9/L);\t标本审核建议:Auto Validation OK,未判断(0.0—0.0);\tC反应蛋白:5mg/L,正常(0.0—10.0mg/L);\t仪器名称:BC6800_1,未判断(0.0—0.0);\t中性粒细胞%:49.0％,偏低(50.0—70.0％);\t单核细胞计数:0.40×10^9/L,正常(0.12—1.0×10^9/L);\t淋巴细胞计数:3.27×10^9/L,正常(0.8—4.0×10^9/L);\t嗜酸性粒细胞%:2.5％,正常(0.5—5.0％);\t淋巴细胞%:42.9％,偏高(20.0—40.0％);\t白细胞计数:7.62x10^9/L,正常(3.69—9.16x10^9/L);\t单核细胞%:5.2％,正常(3.0—10.0％);\n\n###病理报告:\n无\n\n###最后一个在院评估单:\n###在院评估单:\n时间:2019-04-12\n基础评估:1.生活自理能力评估: Barthel指数总分85分。2.活动能力评估: 步态稳定 ；活动状态:活动自如 。 3.意识状况评估:神志: 清醒 ，感知觉未受损（对指令有反应，能准确表达疼痛和不适） 。 4.粘膜与皮肤状况评估:颜色: 正常 ；温度: 正常 ；湿度: 正常（皮肤经常保持干燥，只需常规更换床单） ；皮肤完整性: 完整 。 无 水肿 ；无 静脉炎 ；无 瘙痒；无 麻木；无 灼烧感 。5.疼痛: 无 疼痛 。 6.排泄: 无 失禁 。 7.意外事件评估: 未发生意外事件。 患者昨夜睡眠: 正常 营养状况评估:良好(饮食摄入和平时一样，每餐有蛋白质摄入) ，无营养支持。 危重症程度评估: 无 严重器官系统功能不全。 无 免疫损害。 格拉斯评分: 15分 。 危重症评分: 6分 。 高危因素的筛查 该病人目前不存在跌倒风险 该病人目前不存在压疮风险。 分级护理级别: 该病人分级护理建议为三级护理。\n置管状态:无置管。 【医学元素\\签名\\护士签名2-护理评估】 【医学元素\\签名\\护士签名3-护理评估】\n请分析所给患者的医疗材料，提取并编写其出院小结中的“病程与治疗情况”。输出应为一段文本。\n字段介绍:综合分析患者的医疗记录，包括手术、化疗、报告和当前情况等，以一段文本总结患者住院期间的整体治疗进展。",
    "出院时情况": "###科室类别:\n小儿科\n\n###首次病程记录:\n时间:2019-03-30\n病例特点:4、查体:神清，精神可，查体合作，全身皮肤粘膜无苍白黄染，咽稍红，扁桃体I°大，未见渗出，颈软，气管居中，胸廓无畸形，双肺呼吸音粗，未闻及干湿啰音，左下肺呼吸音稍低，心率112次/分，心律齐，未及明显心脏杂音，腹软无压痛及反跳痛，肠鸣音无亢进，肝脾肋下未及，四肢无畸形，双下肢无水肿，NS（-）。\n###主任医师日常查房记录:\n时间:2019-04-08\n对病情的分析:患儿无发热，仍有咳嗽较前好转，胃纳可，无腹痛、腹泻等不适。 查体:神志清，精神可，查体合作，全身皮肤粘膜无苍白黄染，咽稍红，扁桃体I°大，未见渗出，颈软，气管居中，胸廓无畸形，双肺呼吸音粗，双肺可及湿罗音，左肺显著，心律齐，未及明显心脏杂音，腹软无压痛及反跳痛，肠鸣音无亢进，肝脾肋下未及，四肢无畸形，双下肢无水肿，NS（-）。 辅助检查:暂无新。\n诊疗意见:继续头孢呋辛抗感染，沐舒坦化痰及雾化等对症治疗，明日予以阿奇霉素第二疗程抗感染。\n###主治医师日常查房记录:\n时间:2019-04-12\nTM员工名称TM 主治医生查房:对病情的分析: 目前患儿偶有咳嗽，不剧，无发热、咳痰，无鼻塞、流涕等不适，一般情况可。 查体:神清，精神可，全身皮肤粘膜无苍白黄染，咽稍红，扁桃体I°大，未见渗出，颈软，气管居中，胸廓无畸形，双肺呼吸音粗，未闻及干湿啰音，心律齐，未及明显心脏杂音，腹软无压痛及反跳痛，肠鸣音无亢进，肝脾肋下未及，四肢无畸形，双下肢无水肿，NS（-）。 诊疗意见: 患儿目前一般情况可，明日予以带药出院。\n\n###最后一个在院评估单:\n###在院评估单:\n时间:2019-04-12\n基础评估:1.生活自理能力评估: Barthel指数总分85分。2.活动能力评估: 步态稳定 ；活动状态:活动自如 。 3.意识状况评估:神志: 清醒 ，感知觉未受损（对指令有反应，能准确表达疼痛和不适） 。 4.粘膜与皮肤状况评估:颜色: 正常 ；温度: 正常 ；湿度: 正常（皮肤经常保持干燥，只需常规更换床单） ；皮肤完整性: 完整 。 无 水肿 ；无 静脉炎 ；无 瘙痒；无 麻木；无 灼烧感 。5.疼痛: 无 疼痛 。 6.排泄: 无 失禁 。 7.意外事件评估: 未发生意外事件。 患者昨夜睡眠: 正常 营养状况评估:良好(饮食摄入和平时一样，每餐有蛋白质摄入) ，无营养支持。 危重症程度评估: 无 严重器官系统功能不全。 无 免疫损害。 格拉斯评分: 15分 。 危重症评分: 6分 。 高危因素的筛查 该病人目前不存在跌倒风险 该病人目前不存在压疮风险。 分级护理级别: 该病人分级护理建议为三级护理。\n置管状态:无置管。 【医学元素\\签名\\护士签名2-护理评估】 【医学元素\\签名\\护士签名3-护理评估】\n请从所提供的患者医疗文件中提取出院小结文书里的“出院时情况”部分。请以文本格式输出。\n字段介绍:综合患者的病历信息，描述其出院时的健康状态，包括精神清晰度、伤口愈合程度及其他重要健康指标。",
    "出院后用药建议": "###科室类别:\n小儿科\n\n###出院相关诊断:\n诊断时间:2019-04-12\n诊断类型:出院诊断\n诊断名称:社区获得性肺炎，非重症\n\n诊断时间:2019-04-12\n诊断类型:出院诊断(补充)\n诊断名称:心肌损害\n\n###主治医师首次查房记录:\n时间:2019-03-31\n诊断:社区获得性肺炎，非重症 诊断依据: 1、患儿，女，8岁 2、主诉:发热4天伴咳嗽 3、查体:神清，精神可，查体合作，全身皮肤粘膜无苍白黄染，咽稍红，扁桃体I°大，未见渗出，颈软，气管居中，胸廓无畸形，双肺呼吸音粗，未闻及干湿啰音，左下肺呼吸音稍低，心率112次/分，心律齐，未及明显心脏杂音，腹软无压痛及反跳痛，肠鸣音无亢进，肝脾肋下未及，四肢无畸形，双下肢无水肿，NS（-）。 4、辅检:我院 2019.3.27【甲乙流】阴性 【血常规+CRP】CRP14mg/L, WBC 8.85*10^9/L, N% 75.8%, HB 133g/L, PLT 212*10^9/L 2019.3.30【甲乙流】阴性 【血常规+CRP】CRP24mg/L, WBC 6.91*10^9/L, N% 74.7%, HB 129 g/L, PLT 193*10^9/L 【胸片】 左肺纹理增多模糊，左侧肺门影增大，左肺斑片渗出影，感染？左侧少许胸腔积液可能 鉴别诊断: 1、支原体肺炎:临床表现为发热、干咳，咳嗽症状较为剧烈，辅助检查血常规中血象正常或轻度升高，中性粒细胞为主，严重时伴有CRP升高，胸片可见间质性改变或大灶性变化。该患儿咳嗽伴发热，胸片示右肺炎症，双肺听诊呼吸音粗，可及少许湿罗音，虽肺支IgM阴性，但不能排除，可完善相关病原学检查以明确诊断。 2、肺炎链球菌肺炎:肺炎链球菌感染是儿童细菌性肺炎最常见的病原体。本例患儿病程中咳嗽，高热，咳痰较多，但患儿血常规示白细胞无明显升高，暂不考虑肺炎链球菌感染的可能，待进一步完善病原学检查以排除。\n\n###出院带药:\n医嘱时间:2019-04-12\n医嘱类型名称:临时医嘱\t医嘱项名称:橘红痰咳液(无蔗糖)\t医嘱项规格:10ml*18支/盒\t单次剂量数量:10.0\t单次给药数量:1.0\t给药途径:口服\t给药频次:一日2次\n\n医嘱时间:2019-04-12\n医嘱类型名称:临时医嘱\t医嘱项名称:仙特明滴剂(盐酸西替利嗪滴剂）\t医嘱项规格:50mg/盒\t单次剂量数量:10.0\t单次给药数量:0.2\t给药途径:口服\t给药频次:每晚1次\n\n###异常检验指标:\n报告时间:2019-03-30 13:44:48\n检验详情:D-二聚体定量:0.86mg/L,偏高;\tFg:5.3g/L,偏高;\n\n报告时间:2019-03-30 13:54:17\n检验详情:肌酸激酶:352IU/L,偏高;\t肌酐:43μmol/L,偏低;\t碱性磷酸酶:175IU/L,偏高;\t前白蛋白:120mg/L,偏低;\t白球比例:1.17,偏低;\t天门冬氨酸氨基转移酶:43IU/L,偏高;\t乳酸脱氢酶:338IU/L,偏高;\n\n报告时间:2019-03-31 08:55:55\n检验详情:酮体:阳性(+),偏高;\n\n报告时间:2019-04-01 12:31:10\n检验详情:抗巨细胞病毒IgG:115.60,偏高;\tEB病毒EBNAIgG:325.00U/mL,偏高;\tEB病毒VCAIgG:93.20U/mL,偏高;\n\n报告时间:2019-04-02 09:57:50\n检验详情:C-反应蛋白:19.5mg/L,偏高;\n\n报告时间:2019-04-02 14:06:53\n检验详情:MP:阳性(+),未判断;\n\n报告时间:2019-04-02 16:13:48\n检验详情:甲状腺素(T4):160.51nmol/L,偏高;\n\n报告时间:2019-04-11 08:24:21\n检验详情:乳酸脱氢酶:282IU/L,偏高;\n\n报告时间:2019-04-11 08:36:09\n检验详情:血小板计数:477×10^9/L,偏高;\t中性粒细胞%:49.0％,偏低;\t淋巴细胞%:42.9％,偏高;\n\n###全部检查:\n检查ID:2019033100000116|1\n报告时间:2019-04-01 15:13:40\n描述:放射|平扫|住院CT|胸部CT(薄层) 平扫\n图像所见:左肺见散在斑片状高密度影，境界模糊不清，右肺亦显示少许斑片状渗出。 两肺门区未见异常。 所示气管支气管影正常。 纵隔内未见异常增大的淋巴结。\n图像分析:两肺炎症，左肺明显。请结合临床及其他相关检查，随诊。\n\n检查ID:2019041010001846|1\n报告时间:2019-04-10 14:09:28\n描述:放射|胸部|X-ray平片|胸部 胸部\n图像所见:所示胸廓骨骼及胸壁软组织未见异常。 纵隔及气管居中未见移位。 纵隔未见增宽。 心脏形态大小未见异常。 两膈光整，两肋膈角锐利。 左肺门饱满，右肺门形态大小位置未见异常。 两肺纹理略增多。左肺下野小斑片影。\n图像分析:左下肺炎症，较2019-03-30前片略吸收，请结合临床及其他相关检查。\n\n###最后一个在院评估单:\n###在院评估单:\n时间:2019-04-12\n基础评估:1.生活自理能力评估: Barthel指数总分85分。2.活动能力评估: 步态稳定 ；活动状态:活动自如 。 3.意识状况评估:神志: 清醒 ，感知觉未受损（对指令有反应，能准确表达疼痛和不适） 。 4.粘膜与皮肤状况评估:颜色: 正常 ；温度: 正常 ；湿度: 正常（皮肤经常保持干燥，只需常规更换床单） ；皮肤完整性: 完整 。 无 水肿 ；无 静脉炎 ；无 瘙痒；无 麻木；无 灼烧感 。5.疼痛: 无 疼痛 。 6.排泄: 无 失禁 。 7.意外事件评估: 未发生意外事件。 患者昨夜睡眠: 正常 营养状况评估:良好(饮食摄入和平时一样，每餐有蛋白质摄入) ，无营养支持。 危重症程度评估: 无 严重器官系统功能不全。 无 免疫损害。 格拉斯评分: 15分 。 危重症评分: 6分 。 高危因素的筛查 该病人目前不存在跌倒风险 该病人目前不存在压疮风险。 分级护理级别: 该病人分级护理建议为三级护理。\n置管状态:无置管。 【医学元素\\签名\\护士签名2-护理评估】 【医学元素\\签名\\护士签名3-护理评估】\n请根据所给患者的医疗文书，生成该患者出院小结文书中的“出院后用药建议”字段内容。确保输出为一段文本。\n字段介绍:为了清楚展示该字段，应以逐条编号的格式呈现，例如用‘1.’, ‘2.’, ‘3.’等数字明确标出每一项建议。\n撰写建议:请提醒患者出院后的日常注意事项；描述患者的出院带药；此外，核对患者相应报告是否出齐；查看患者的报告中是否有异常情况，给出随诊与就诊建议；根据患者情况给出后续就诊科室。"
  }
}