{
  "19031800000201": {
    "基本信息": {
      "出院诊断": "社区获得性肺炎,非重症,肺炎支原体性肺炎",
      "床号": "64977",
      "科别": "儿科病区",
      "入院时间": "2019-03-18",
      "出院时间": "无法判断",
      "姓名": "常柳",
      "性别": "女",
      "年龄": "6",
      "住院号": "z09235",
      "入院诊断": ""
    },
    "入院时简要病史": "患儿入院前2月无明显诱因下出现咳嗽，偶有阵发性，不剧，涕多伴有鼻塞，无痰，咳嗽无明显规律，与运动等无相关性，无气促喘息，无空空样咳，咳毕无鸡鸣样喘息，无明显加重，故未予特殊处理，仅口服中药制剂调理，至入院前3天患儿突然出现发热，热峰最高38.8°，热距10-12小时，无明显畏寒寒战，同时咳嗽较前加重，较频繁稍剧，咳痰、涕多明显，余同前，3-15仁济南院就诊完善血常规WBC 6.15*10 9/L，N%59.4% ，L%24.7%，HB 139g/L，PLT331*10^9/l ,CRP ＜2.5mg/l，考虑咽炎及鼻炎，予内舒拿等对症治疗，但患儿发热及咳嗽无明显好转，故再次就诊我院急诊完善 WBC9.39*109/L，N%71.8%，EOS% 6.4%，HB123g/L，PLT241*10^9/l,CRP＜9mg/l,胸部：胸部 两肺纹理增多模糊，两肺斑点片状模糊影，考虑炎症改变,考虑支气管肺炎，故收治入院。追问病史患儿既往鼻炎及哮喘病史，3岁至4岁期间曾间断雾化治疗哮喘，近2年无喘息反复。 病程中患儿精神反应可，胃纳可，二便正常，无体重减轻。",
    "体检摘要": "神清，精神可，全身皮肤黏膜未见黄染，未见苍白，未见瘀点瘀斑，浅表淋巴结未触及肿大。口腔黏膜光整，咽红，双侧扁桃体II°，无渗出。RR 16次/分，胸廓无畸形，三凹征（-），双侧呼吸音粗，左右对称，左下肺闻及少湿性啰音，HR110次/分，心音有力，心律齐，未闻及异常杂音。腹软，无压痛、反跳痛，肝脾肋下未及肿大。四肢、脊柱未见畸形。脑膜刺激征（-），NS（-）",
    "生命体征": {
      "T": "38.5",
      "P": "122",
      "R": "20",
      "BP高": "107",
      "BP低": "75"
    },
    "住院期间医疗情况": "【血常规】 白细胞计数 7.4×109/L(参考值3.80--10.00×109/L) 中性粒细胞% 75.6％(参考值50.0%--70.0%) 淋巴细胞% 15.0％(参考值20.0％--40.0％) 单核细胞% 5.2％(参考值3.0%--10.0%) 红细胞计数 4.43×1012/L(参考值3.80--5.10×1012/L) 血红蛋白 133g/L(参考值110--150g/L) 红细胞比容 0.382(参考值0.370--0.430) 平均红细胞体积 75.5fl(参考值82.0--100.0fl) 平均血红蛋白量 25.3pg(参考值26.0--31.0pg) 平均血红蛋白浓度 319g/L(参考值310--360g/L) 红细胞分布宽度 13.7％(参考值11.0%--15.0%) 血小板计数 201×109/L(参考值100--300×109/L) 【生化】 葡萄糖 4.64mmol/L(参考值3.90--6.10mmol/L) 丙氨酸氨基转移酶 11IU/L(参考值10--64IU/L) 天门冬氨酸氨基转移酶 37IU/L(参考值8--40IU/L) 碱性磷酸酶 271↑IU/L(参考值38--126IU/L) γ-谷氨酰基转移酶 11IU/L(参考值7--64IU/L) 总胆红素 6.2μmol/L(参考值4.7--24μmol/L) 直接胆红素 0.9μmol/L(参考值0--6.8μmol/L) 总蛋白 70g/L(参考值60--83g/L) 白蛋白 46g/L(参考值35--55g/L) 白球比例 1.92(参考值1.25--2.50) 胆汁酸 4.4μmol/L(参考值1.0--10.0μmol/L) 尿素 2.4↓mmol/L(参考值2.5--7.1mmol/L) 肌酐 33↓μmol/L(参考值53--97μmol/L) 尿酸 185μmol/L(参考值160--430μmol/L) 钠 143mmol/L(参考值130--147mmol/L) 钾 3.74mmol/L(参考值3.50--5.10mmol/L) 氯 107mmol/L(参考值96--108mmol/L) 二氧化碳 24.0mmol/L(参考值21.0--31.0mmol/L) 钙 2.30mmol/L(参考值2.00--2.75mmol/L) 磷 1.24mmol/L(参考值0.80--1.60mmol/L) 血清镁 0.89mmol/L(参考值0.74--1.03mmol/L) 胱抑素C 0.70mg/L(参考值0.55--1.07mg/L) 估算肾小球滤过率 169.8ml/min/1.73m2(参考值) 【DIC】 APTT 36.0秒(参考值22.3--38.7秒) PT 12.4秒(参考值10.0--16.0秒) INR 1.05(参考值/) TT 18.50秒(参考值14.00--21.00秒) Fg 2.3g/L(参考值1.8--3.5g/L) 纤维蛋白降解产物 1.3mg/L(参考值0.0--5.0mg/L) D-二聚体定量 0.38mg/L(参考值<0.55mg/L) 【CRP】 C反应蛋白 1.2mg/L(参考值0--8mg/L) 【降钙素原】 <0.05ng/mL(参考值<0.5ng/mL) 【血常规】 白细胞计数 7.4×109/L(参考值3.80--10.00×109/L) 中性粒细胞% 75.6％(参考值50.0%--70.0%) 淋巴细胞% 15.0％(参考值20.0%--40.0%) 单核细胞% 5.2％(参考值3.0%--10.0%) 嗜酸性粒细胞% 1.3％(参考值0.5%--5.0%) 嗜碱性粒细胞% 0.0％(参考值<1.0%) 中性粒细胞计数 5.62×109/L(参考值2.00--7.00×109/L) 淋巴细胞计数 1.05×109/L(参考值0.80--3.80×109/L) 单核细胞计数 0.30×109/L(参考值0.12--0.90×109/L) 嗜酸性粒细胞计数 0.05×109/L(参考值0.00--0.08×109/L) 嗜碱性粒细胞计数 0.00×109/L(参考值<1.00×109/L) 红细胞计数 4.43×1012/L(参考值3.80--5.10×1012/L) 血红蛋白 133g/L(参考值110--150g/L) 红细胞比容 0.382(参考值0.370--0.430) 平均红细胞体积 75.5fl(参考值82.0--100.0fl) 平均血红蛋白量 25.3pg(参考值26.0--31.0pg) 平均血红蛋白浓度 319g/L(参考值310--360g/L) 红细胞分布宽度 13.7％(参考值11.0%--15.0%) 血小板计数 201×109/L(参考值100--300×109/L) 【CRP】 C反应蛋白 1.2mg/L(参考值0--8mg/L) 【降钙素原】 <0.05ng/mL(参考值<0.5ng/mL) 【EB病毒定量】 EB病毒 ＜5.0×102copies/ml(参考值(-10000.0--99999.0copies/ml) 【支原体定量】 肺炎支原体 <1.0×103copies/ml(参考值(-10000.0--99999.0copies/ml) 【肺炎支原体抗体定量】 阳性(+)↑(参考值阴性(-)) 【肺支抗体】 阳性(+)↑(参考值阴性(-)) 【抗甲流病毒抗体定量】 阴性(-)(参考值阴性(-)) 【抗R合胞病毒抗体定量】 阴性(-)(参考值阴性(-)) 【抗腺病毒抗体定量】 阴性(-)(参考值阴性(-)) 【抗Q热立克次体抗体定量】 阴性(-)(参考值阴性(-)) 【抗副流感1,2,3型病毒抗体定量】 阴性(-)(参考值阴性(-)) 【抗巨细胞病毒抗体定量】 179.60↑(参考值阴性(-)) 【抗EB病毒抗体定量】 EB病毒EAIgG 5.96U/mL(参考值阴性(-)) EB病毒EBVIgM <10.00(参考值阴性(-)) EB病毒VCAIgG <10.00U/mL(参考值阴性(-)) EB病毒EBNAIgG <3.00U/mL(参考值阴性(-)) 【抗EB病毒IgM】 阳性(+)↑(参考值阴性(-)) 【抗EB病毒IgG】 阴性(-)(参考值阴性(-)) 【抗EB病毒IgA】 阴性(-)(参考值阴性(-)) 【抗EB病毒IgM】 阴性(-)(参考值阴性(-)) 【抗EB病毒IgG】 阴性(-)(参考值阴性(-)) 【抗EB病毒IgA】 阴性(-)(参考值阴性(-)) 【抗EB病毒IgG】 阴性(-)(参考值阴性(-)) 【抗EB病毒IgM】 阴性(-)(参考值阴性(-)) 【抗EB病毒IgG】 阴性(-)(参考值阴性(-)) 【抗EB病毒IgA】 阴性(-)(参考值阴性(-)) 【抗EB病毒IgM】 阴性(-)(参考值阴性(-)) 【抗EB病毒IgG】 阴性(-)(参考值阴性(-)) 【抗EB病毒IgA】 阴性(-)(参考值阴性(-)) 【抗EB病毒IgM】 阴性(-)(参考值阴性(-)) 【抗EB病毒IgG】 阴性(-)(参考值阴性(-)) 【抗EB病毒IgA】 阴性(-)(参考值阴性(-)) 【抗EB病毒IgM】 阴性(-)(参考值阴性(-)) 【抗EB病毒IgG】 阴性(-)(参考值阴性(-)) 【抗EB病毒IgA】 阴性(-)(参考值阴性(-)) 【抗EB病毒IgM】 阴性(-)(参考值阴性(-)) 【抗EB病毒IgG】 阴性(-)(参考值阴性(-)) 【抗EB病毒IgA】 阴性(-)(参考值阴性(-)) 【抗EB病毒IgM】 阴性(-)(参考值阴性(-)) 【抗EB病毒IgG】 阴性(-)(参考值阴性(-)) 【抗EB病毒IgA】 阴性(-)(参考值阴性(-)) 【抗EB病毒IgM】 阴性(-)(参考值阴性(-)) 【抗EB病毒IgG】 阴性(-)(参考值阴性(-)) 【抗EB病毒IgA】 阴性(-)(参考值阴性(-)) 【抗EB病毒IgM】 阴性(-)(参考值阴性(-)) 【抗EB病毒IgG】 阴性(-)(参考值阴性(-)) 【抗EB病毒IgA】 阴性(-)(参考值阴性(-)) 【抗EB病毒IgM】 阴性(-)(参考值阴性(-)) 【抗EB病毒IgG】 阴性(-)(参考值阴性(-)) 【抗EB病毒IgA】 阴性(-)(参考值阴性(-)) 【抗EB病毒IgM】 阴性(-)(参考值阴性(-)) 【抗EB病毒IgG】 阴性(-)(参考值阴性(-)) 【抗EB病毒IgA】 阴性(-)(参考值阴性(-)) 【抗EB病毒IgM】 阴性(-)(参考值阴性(-)) 【抗EB病毒IgG】 阴性(-)(参考值阴性(-)) 【抗EB病毒IgA】 阴性(-)(参考值阴性(-)) 【抗EB病毒IgM】 阴性(-)(参考值阴性(-)) 【抗EB病毒IgG】 阴性(-)(参考值阴性(-)) 【抗EB病毒IgA】 阴性(-)(参考值阴性(-)) 【抗EB病毒IgM】 阴性(-)(参考值阴性(-)) 【抗EB病毒IgG】 阴性(-)(参考值阴性(-)) 【抗EB病毒IgA】 阴性(-)(参考值阴性(-)) 【抗EB病毒IgM】 阴性(-)(参考值阴性(-)) 【抗EB病毒IgG】 阴性(-)(参考值阴性(-)) 【抗EB病毒IgA】 阴性(-)(参考值阴性(-)) 【抗EB病毒IgM】 阴性(-)(参考值阴性(-)) 【抗EB病毒IgG】 阴性(-)(参考值阴性(-)) 【抗EB病毒IgA】 阴性(-)(参考值阴性(-)) 【抗EB病毒IgM】 阴性(-)(参考值阴性(-)) 【抗EB病毒IgG】 阴性(-)(参考值阴性(-)) 【抗EB病毒IgA】 阴性(-)(参考值阴性(-)) 【抗EB病毒IgM】 阴性(-)(参考值阴性(-)) 【抗EB病毒IgG】 阴性(-)(参考值阴性(-)) 【抗EB病毒IgA】 阴性(-)(参考值阴性(-)) 【抗EB病毒IgM】 阴性(-)(参考值阴性(-)) 【抗EB病毒IgG】 阴性(-)(参考值阴性(-)) 【抗EB病毒IgA】 阴性(-)(参考值阴性(-)) 【抗EB病毒IgM】 阴性(-)(参考值阴性(-)) 【抗EB病毒IgG】 阴性(-)(参考值阴性(-)) 【抗EB病毒IgA】 阴性(-)(参考值阴性(-)) 【抗EB病毒IgM】 阴性(-)(参考值阴性(-)) 【抗EB病毒IgG】 阴性(-)(参考值阴性(-)) 【抗EB病毒IgA】 阴性(-)(参考值阴性(-)) 【抗EB病毒IgM】 阴性(-)(参考值阴性(-)) 【抗EB病毒IgG】 阴性(-)(参考值阴性(-)) 【抗EB病毒IgA】 阴性(-)(参考值阴性(-)) 【抗EB病毒IgM】 阴性(-)(参考值阴性(-)) 【抗EB病毒IgG】 阴性(-)(参考值阴性(-)) 【抗EB病毒IgA】 阴性(-)(参考值阴性(-)) 【抗EB病毒IgM】 阴性(-)(参考值阴性(-)) 【抗EB病毒IgG】 阴性(-)(参考值阴性(-)) 【抗EB病毒IgA】 阴性(-)(参考值阴性(-)) 【抗EB病毒IgM】 阴性(-)(参考值阴性(-)) 【抗EB病毒IgG】 阴性(-)(参考值阴性(-)) 【抗EB病毒IgA】 阴性(-)(参考值阴性(-)) 【抗EB病毒IgM】 阴性(-)(参考值阴性(-)) 【抗EB病毒IgG】 阴性(-)(参考值阴性(-)) 【抗EB病毒IgA】 阴性(-)(参考值阴性(-)) 【抗EB病毒IgM】 阴性(-)(参考值阴性(-)) 【抗EB病毒IgG】 阴性(-)(参考值阴性(-)) 【抗EB病毒IgA】 阴性(-)(参考值阴性(-)) 【抗EB病毒IgM】 阴性(-)(参考值阴性(-)) 【抗EB病毒IgG】 阴性(-)(参考值阴性(-)) 【抗EB病毒IgA】 阴性(-)(参考值阴性(-)) 【抗EB病毒IgM】 阴性(-)(参考值阴性(-)) 【抗EB病毒IgG】 阴性(-)(参考值阴性(-)) 【抗EB病毒IgA】 阴性(-)(参考值阴性(-)) 【抗EB病毒IgM】 阴性(-)(参考值阴性(-)) 【抗EB病毒IgG】 阴性(-)(参考值阴性(-)) 【抗EB病毒IgA】 阴性(-)(参考值阴性(-)) 【抗EB病毒IgM】 阴性(-)(参考值阴性(-)) 【抗EB病毒IgG】 阴性(-)(参考值阴性(-)) 【抗EB病毒IgA】 阴性(-)(参考值阴性(-)) 【抗EB病毒IgM】 阴性(-)(参考值阴性(-)) 【抗EB病毒IgG】 阴性(-)(参考值阴性(-)) 【抗EB病毒IgA】 阴性(-)(参考值阴性(-)) 【抗EB病毒IgM】",
    "出院时情况": "患儿现体温平稳，偶咳，无痰，精神及胃纳可，二便无殊。 查体：神清，精神可，全身皮肤黏膜未见黄染，未见苍白，未见瘀点瘀斑，浅表淋巴结未触及肿大。口腔黏膜光整，咽红，咽后壁滤泡增生，双侧扁桃体II°肿大，无渗出。RR 18次/分，胸廓无畸形，三凹征（-），双侧呼吸音粗，左右对称，未闻及明显啰音。HR 104次/分，心音有力，心律齐，未闻及异常杂音。腹软，无压痛、反跳痛，肝脾肋下未及肿大。四肢、脊柱未见畸形。脑膜刺激征（-），NS（-）。",
    "病程与治疗情况": "入院后完善相关检查，排除禁忌后予阿奇霉素抗感染，雾化对症止咳化痰，孟鲁斯特纳及西替利嗪抗过敏，雾化治疗后患儿咳嗽较前好转，体温平稳，上级医师示，如无殊，拟明日上午出院，嘱门诊定期随访。",
    "出院后用药建议": "1、注意休息，避免感染，避免接触感冒人群； 2、出院后2周儿科门诊随访，不适及时就诊。",
    "病人信息": {
      "姓名": "常柳",
      "性别": "女",
      "科室": "儿科病区",
      "床号": "64977",
      "住院号": "z09235",
      "住院流水号": "19031800000201",
      "年龄": "6",
      "出生年月": "",
      "入院时间": "2019-03-18",
      "出院时间": "无法判断"
    }
  }
}